mailcore/__init__.py
mailcore/attachment.py
mailcore/body.py
mailcore/draft.py
mailcore/email_address.py
mailcore/exceptions.py
mailcore/folder.py
mailcore/mailbox.py
mailcore/message.py
mailcore/message_list.py
mailcore/protocols.py
mailcore/py.typed
mailcore/query.py
mailcore/types.py
mailcore-0.1.0.dist-info/METADATA
mailcore-0.1.0.dist-info/WHEEL
mailcore-0.1.0.dist-info/licenses/LICENSE
mailcore-0.1.0.dist-info/RECORD
