Metadata-Version: 2.4
Name: mailcore
Version: 0.1.0
Summary: A Python email library designed for intuitive email operations
Author-email: "Hans Christian v. Stockhausen" <hc@vst.io>
License: MIT
License-File: LICENSE
Requires-Python: >=3.10
Provides-Extra: dev
Requires-Dist: detect-secrets; extra == 'dev'
Requires-Dist: mypy>=1.0.0; extra == 'dev'
Requires-Dist: pre-commit; extra == 'dev'
Requires-Dist: pytest-asyncio>=0.21.0; extra == 'dev'
Requires-Dist: pytest-cov>=4.0.0; extra == 'dev'
Requires-Dist: pytest>=7.0.0; extra == 'dev'
Requires-Dist: ruff>=0.1.0; extra == 'dev'
